fmflow/__init__.py
fmflow/core/__init__.py
fmflow/core/array/classes.py
fmflow/core/array/decorators.py
fmflow/core/array/functions.py
fmflow/core/cube/classes.py
fmflow/core/cube/functions.py
fmflow/core/spectrum/classes.py
fmflow/core/spectrum/functions.py
fmflow/data/am.yaml
fmflow/data/aste_antennalog.yaml
fmflow/data/aste_backendlog_common.yaml
fmflow/data/aste_backendlog_mac.yaml
fmflow/data/aste_fmlolog.yaml
fmflow/data/nro45m_antennalog.yaml
fmflow/data/nro45m_backendlog_common.yaml
fmflow/data/nro45m_backendlog_sam45.yaml
fmflow/data/nro45m_fmlolog.yaml
fmflow/data/obsinfo.yaml
fmflow/fits/__init__.py
fmflow/fits/aste/functions.py
fmflow/fits/functions.py
fmflow/fits/nro45m/functions.py
fmflow/logging/__init__.py
fmflow/models/__init__.py
fmflow/models/astrosignal/classes.py
fmflow/models/astrosignal/functions.py
fmflow/models/atmosphere/classes.py
fmflow/models/atmosphere/functions.py
fmflow/models/commonmode/classes.py
fmflow/models/commonmode/functions.py
fmflow/models/gain/classes.py
fmflow/models/gain/functions.py
fmflow/utils/__init__.py
fmflow/utils/binary/classes.py
fmflow/utils/convergence/classes.py
fmflow/utils/datetime/classes.py
fmflow/utils/fits/functions.py
fmflow/utils/misc/functions.py
fmflow/utils/ndarray/functions.py
fmflow-0.5.0.dist-info/LICENSE
fmflow-0.5.0.dist-info/METADATA
fmflow-0.5.0.dist-info/WHEEL
fmflow-0.5.0.dist-info/RECORD
